[
  {
    "intent": "LIST_PRODUCTS",
    "sampleUtterances": [
      "shop bán gì",
      "có bán sản phẩm gì",
      "bạn có những loại nào",
      "liệt kê sản phẩm"
    ],
    "tool": "listProducts",
    "status": "active"
  },
  {
    "intent": "TOP_RENTED",
    "sampleUtterances": [
      "sản phẩm ưu tú",
      "đồ thuê nhiều nhất",
      "top thuê",
      "mẫu hot nhất"
    ],
    "tool": "topRented",
    "status": "active"
  },
  {
    "intent": "MY_ORDER",
    "sampleUtterances": [
      "đơn hàng của tôi",
      "kiểm tra đơn",
      "tra cứu đơn",
      "check my order"
    ],
    "tool": "myOrder",
    "status": "active"
  }
]

